sten/__init__.py
sten/formats.py
sten/patches.py
sten/sten.py
sten-0.0.4.dist-info/METADATA
sten-0.0.4.dist-info/WHEEL
sten-0.0.4.dist-info/top_level.txt
sten-0.0.4.dist-info/RECORD
